nusterai/__init__.py
nusterai/llm_wrappers.py
nusterai/routing.py
tests/__init__.py
tests/test_routing.py
nusterai-0.1.0.dist-info/LICENSE
nusterai-0.1.0.dist-info/METADATA
nusterai-0.1.0.dist-info/WHEEL
nusterai-0.1.0.dist-info/top_level.txt
nusterai-0.1.0.dist-info/RECORD
